devshakti_ai-0.1.2.dist-info/licenses/LICENSE
shakti/__init__.py
shakti/chat.py
shakti/client.py
devshakti_ai-0.1.2.dist-info/METADATA
devshakti_ai-0.1.2.dist-info/WHEEL
devshakti_ai-0.1.2.dist-info/top_level.txt
devshakti_ai-0.1.2.dist-info/RECORD
