Metadata-Version: 2.4
Name: devshakti-ai
Version: 0.1.2
Summary: Python SDK for Shakti LLM API - OpenAI compatible
Home-page: https://shakti-one.vercel.app
Author: Shivnath Tathe
Author-email: sptathe2001@gmail.com
Keywords: shakti ai llm api sdk openai
Classifier: Programming Language :: Python :: 3
Classifier: Operating System :: OS Independent
Requires-Python: >=3.7
License-File: LICENSE
Requires-Dist: requests>=2.25.0
Dynamic: author
Dynamic: author-email
Dynamic: classifier
Dynamic: description
Dynamic: description-content-type
Dynamic: home-page
Dynamic: keywords
Dynamic: license-file
Dynamic: requires-dist
Dynamic: requires-python
Dynamic: summary
